folder/__init__.py
folder/cp.py
folder/project.py
folder-0.0.1.dist-info/METADATA
folder-0.0.1.dist-info/WHEEL
folder-0.0.1.dist-info/top_level.txt
folder-0.0.1.dist-info/RECORD
