Metadata-Version: 2.1
Name: folder
Version: 0.0.1
Summary: UNKNOWN
Home-page: UNKNOWN
Author: Aditta Das Nishad
Author-email: nishad009adi@gmail.com
License: MIT
Platform: UNKNOWN
